stackit/intake/__init__.py
stackit/intake/api/__init__.py
stackit/intake/api/default_api.py
stackit/intake/api_client.py
stackit/intake/api_response.py
stackit/intake/configuration.py
stackit/intake/exceptions.py
stackit/intake/models/__init__.py
stackit/intake/models/catalog_auth.py
stackit/intake/models/catalog_auth_patch.py
stackit/intake/models/catalog_auth_type.py
stackit/intake/models/client_config.py
stackit/intake/models/create_intake_payload.py
stackit/intake/models/create_intake_runner_payload.py
stackit/intake/models/create_intake_user_payload.py
stackit/intake/models/dremio_auth.py
stackit/intake/models/dremio_auth_patch.py
stackit/intake/models/intake_catalog.py
stackit/intake/models/intake_catalog_patch.py
stackit/intake/models/intake_response.py
stackit/intake/models/intake_runner_response.py
stackit/intake/models/intake_user_response.py
stackit/intake/models/list_intake_runners_response.py
stackit/intake/models/list_intake_users_response.py
stackit/intake/models/list_intakes_response.py
stackit/intake/models/partitioning_type.py
stackit/intake/models/update_intake_payload.py
stackit/intake/models/update_intake_runner_payload.py
stackit/intake/models/update_intake_user_payload.py
stackit/intake/models/user_type.py
stackit/intake/py.typed
stackit/intake/rest.py
stackit_intake-0.2.1.dist-info/METADATA
stackit_intake-0.2.1.dist-info/WHEEL
stackit_intake-0.2.1.dist-info/licenses/LICENSE.md
stackit_intake-0.2.1.dist-info/licenses/NOTICE.txt
stackit_intake-0.2.1.dist-info/RECORD
